integrator/__init__.py
integrator/sdk.py
integrator/types.py
dachintegrator-1.0.0.dist-info/METADATA
dachintegrator-1.0.0.dist-info/WHEEL
dachintegrator-1.0.0.dist-info/top_level.txt
dachintegrator-1.0.0.dist-info/RECORD
