Metadata-Version: 2.4
Name: dachintegrator
Version: 1.0.0
Summary: Python SDK class for Django to create convenient CRUD and Non CRUD third-party integrations
Author-email: Dachi Vadachkoria <dachi.vadachkoria@gmail.com>
Project-URL: Homepage, https://github.com/dachivadachkoria/integrator
Requires-Python: >=3.7
Requires-Dist: requests==2.28.1
Requires-Dist: django>=4.0
